{
  "2G": [
    "2G"
  ],
  "3G": [
    "3G"
  ],
  "3TV": [
    "3TV"
  ],
  "3bezel": [
    "3bezel"
  ],
  "4G": [
    "4G"
  ],
  "ACL": [
    "SLL"
  ],
  "AE": [
    "AE"
  ],
  "AES": [
    "AES"
  ],
  "AES128": [
    "AES128"
  ],
  "AES256": [
    "AES256"
  ],
  "AF": [
    "AF"
  ],
  "AFHTTP": [
    "AFHttp"
  ],
  "AFJSON": [
    "AFJson"
  ],
  "AFNETWORKING": [
    "AFNETWORKING"
  ],
  "AFNSURL": [
    "AFNSUrl"
  ],
  "AFSSL": [
    "AFSSL"
  ],
  "AFURL": [
    "AFUrl"
  ],
  "AFXML": [
    "AFXml"
  ],
  "AN": [
    "AN"
  ],
  "ARG": [
    "ARG"
  ],
  "AUOTLOGIN": [
    "AutoLogin"
  ],
  "AVPBKDF": [
    "go"
  ],
  "AVTS": [
    "tvs"
  ],
  "Acc": [
    "Tac"
  ],
  "Accont": [
    "Account"
  ],
  "Accout": [
    "Zanghao"
  ],
  "Acount": [
    "zhanghao"
  ],
  "Actoin": [
    "Actoin"
  ],
  "Aizhi": [
    "Ahui"
  ],
  "Alg": [
    "Alg"
  ],
  "Algorithm": [
    "al"
  ],
  "Analytics": [
    "seached"
  ],
  "And": [
    "with"
  ],
  "Annoucement": [
    "Annoucement"
  ],
  "Anonymously": [
    "ANmostly"
  ],
  "App": [
    "App"
  ],
  "Args": [
    "mag"
  ],
  "Arr": [
    "Array"
  ],
  "Assitive": [
    "assistant"
  ],
  "Aui": [
    "_"
  ],
  "Auth": [
    "Auth"
  ],
  "Autorelease": [
    "Autorelease"
  ],
  "Autoreleased": [
    "Autoreleased"
  ],
  "Azhi": [
    "Azhihui"
  ],
  "Azhihui": [
    "Azhihui"
  ],
  "BASE64": [
    "BASE64"
  ],
  "Bandwidth": [
    "BandWidth"
  ],
  "Batr": [
    "bar"
  ],
  "Bezier": [
    "Bezier"
  ],
  "Boolean": [
    "sure"
  ],
  "Botton": [
    "Button"
  ],
  "Brn": [
    "Button"
  ],
  "Bt": [
    "Button"
  ],
  "Btn": [
    "Button"
  ],
  "Btnclick": [
    "actionBtnClick"
  ],
  "Bugly": [
    "Bugly"
  ],
  "Bytes": [
    "Bytes"
  ],
  "CB": [
    "Center"
  ],
  "CBS": [
    "CBS"
  ],
  "CCPRF": [
    "CCPRF"
  ],
  "CGJ": [
    "Tmp"
  ],
  "CN": [
    "NI"
  ],
  "COLSED": [
    "closed"
  ],
  "CQL": [
    "SQB"
  ],
  "CRLF": [
    "CRLF"
  ],
  "Cannot": [
    "Cannot"
  ],
  "Captcha": [
    "captmas"
  ],
  "Cdata": [
    "Csoure"
  ],
  "Cer": [
    "Cer"
  ],
  "Cir": [
    "Yuan"
  ],
  "Clcik": [
    "Action"
  ],
  "Clik": [
    "Action"
  ],
  "Cneter": [
    "Center"
  ],
  "Comit": [
    "Commit"
  ],
  "Coordinator": [
    "minro"
  ],
  "Costom": [
    "Custom"
  ],
  "Countting": [
    "jishuan"
  ],
  "Coutting": [
    "jishuan"
  ],
  "Crypt": [
    "Cryptor"
  ],
  "Cryptor+": [
    "Cryptor"
  ],
  "Cryptor-": [
    "Cryptor"
  ],
  "Cstr": [
    "sStr"
  ],
  "DK": [
    "dk"
  ],
  "DXRGB": [
    "rbg"
  ],
  "DXRGBACOLOR": [
    "DXRGBACOLOR"
  ],
  "Databases": [
    "DataSource"
  ],
  "Debug": [
    "Debug"
  ],
  "Decryptor": [
    "Decrypt"
  ],
  "Delimiters": [
    "Delimiter"
  ],
  "Desc": [
    "Desc"
  ],
  "Description": [
    "Description"
  ],
  "Dev": [
    "Developer"
  ],
  "Deviceu": [
    "device"
  ],
  "Dic": [
    "Dic"
  ],
  "Dict": [
    "nary"
  ],
  "Didclick": [
    "DidClick"
  ],
  "Dir": [
    "DICT"
  ],
  "Directory": [
    "dict"
  ],
  "Downloader": [
    "Download"
  ],
  "Dt": [
    "Des"
  ],
  "Dview": [
    "View"
  ],
  "EWAN": [
    "EWAN"
  ],
  "Else": [
    "some"
  ],
  "Encapsulation": [
    "Encapsulation"
  ],
  "Encr": [
    "encrypt"
  ],
  "Encryptor": [
    "Encrypt"
  ],
  "Entity": [
    "total"
  ],
  "Enum": [
    "Enum"
  ],
  "Ext": [
    "Ext"
  ],
  "FD": [
    "find"
  ],
  "FIFO": [
    "FIFO"
  ],
  "FMDB": [
    "FD"
  ],
  "FMT": [
    "FMT"
  ],
  "FWD": [
    "FWD"
  ],
  "Feild": [
    "feil"
  ],
  "Fel": [
    "inputfFel"
  ],
  "Fi": [
    "Fi"
  ],
  "Followees": [
    "follwwo"
  ],
  "For": [
    "As"
  ],
  "Formatter": [
    "Formatter"
  ],
  "Friendship": [
    "pengyou"
  ],
  "From": [
    "From"
  ],
  "Func": [
    "Fution"
  ],
  "GBJH": [
    "Game"
  ],
  "GBJHMP": [
    "Game"
  ],
  "Geo": [
    "Loca"
  ],
  "Getter": [
    "getset"
  ],
  "Gming": [
    "Gaming"
  ],
  "Gmlimit": [
    "GameLimit"
  ],
  "Gogo": [
    "go"
  ],
  "Goto": [
    "go"
  ],
  "Guid": [
    "Guid"
  ],
  "H5": [
    "H5"
  ],
  "HEXCOLOR": [
    "HEXCOLOR"
  ],
  "HMAC": [
    "HMAC"
  ],
  "HTTP": [
    "Http"
  ],
  "HU": [
    "Hud"
  ],
  "HUD": [
    "Hud"
  ],
  "Hangqing": [
    "Maketing"
  ],
  "Hostname": [
    "HostName"
  ],
  "Huati": [
    "Huati"
  ],
  "Hzhishu": [
    "Tmath"
  ],
  "IDV": [
    "IdView"
  ],
  "IM": [
    "SMS"
  ],
  "INC": [
    "TCN"
  ],
  "IO": [
    "Io"
  ],
  "IOS": [
    "IOS"
  ],
  "IPHONEX": [
    "IPHONEX"
  ],
  "IQIYI": [
    "one"
  ],
  "Identifier": [
    "symbol"
  ],
  "Idfa": [
    "Idfa"
  ],
  "Idx": [
    "index"
  ],
  "If": [
    "When"
  ],
  "Imagefor": [
    "ImageWith"
  ],
  "Imei": [
    "Imei"
  ],
  "Img": [
    "Image"
  ],
  "Imgv": [
    "images"
  ],
  "Impl": [
    "import"
  ],
  "Inbox": [
    "inputbox"
  ],
  "Incremental": [
    "input"
  ],
  "Init": [
    "Init"
  ],
  "Initial": [
    "Init"
  ],
  "Instrict": [
    "Instrict"
  ],
  "Int": [
    "up"
  ],
  "Inte": [
    "Inter"
  ],
  "Interaction": [
    "Interacte"
  ],
  "Inview": [
    "InView"
  ],
  "Isfrom": [
    "isForm"
  ],
  "Isi": [
    "sI"
  ],
  "JD": [
    "TN"
  ],
  "JN": [
    "ST"
  ],
  "Jia": [
    "Jia"
  ],
  "Jian": [
    "recocom"
  ],
  "Json": [
    "Json"
  ],
  "KAPPH": [
    "kKappHeight"
  ],
  "KAPPW": [
    "Kappwideth"
  ],
  "Kbg": [
    "Kgroud"
  ],
  "Kcurrent": [
    "current"
  ],
  "Kerror": [
    "error"
  ],
  "Keyboard": [
    "board"
  ],
  "Keychain": [
    "Keychain"
  ],
  "Kglobe": [
    "KALLcorlor"
  ],
  "Kgotologinvc": [
    "KpreGo"
  ],
  "Kit+": [
    "Kit"
  ],
  "Kname": [
    "name"
  ],
  "Kplace": [
    "Khohold"
  ],
  "LC": [
    "LC"
  ],
  "LCURL": [
    "LCURL"
  ],
  "LIFO": [
    "lifo"
  ],
  "Lable": [
    "Label"
  ],
  "Landscape": [
    "Landscape"
  ],
  "Lg": [
    "Delu"
  ],
  "Lib": [
    "Lib"
  ],
  "Login": [
    "Enter"
  ],
  "MD5": [
    "MD"
  ],
  "Magin": [
    "seperot"
  ],
  "Maintainance": [
    "Maintainance"
  ],
  "Majia": [
    "Majia"
  ],
  "Meta": [
    "real"
  ],
  "Migrations": [
    "midrations"
  ],
  "Milli": [
    "fill"
  ],
  "Mima": [
    "Secre"
  ],
  "Mine": [
    "ondata"
  ],
  "Misconfigured": [
    "mic"
  ],
  "Money": [
    "Money"
  ],
  "Monoliths": [
    "Monolith"
  ],
  "Msg": [
    "Message"
  ],
  "Multipart": [
    "MultiPart"
  ],
  "Mytopic": [
    "Huati"
  ],
  "NAL": [
    "NAL"
  ],
  "Nat": [
    "Net"
  ],
  "Nav": [
    "Navigation"
  ],
  "Networking": [
    "Net"
  ],
  "None": [
    "None"
  ],
  "Notifier": [
    "notifition"
  ],
  "Nowyyyymmdd": [
    "newdate"
  ],
  "Num": [
    "Number"
  ],
  "OSSTATUS": [
    "OSSTATUS"
  ],
  "OSX": [
    "OSX"
  ],
  "Obic": [
    "Objc"
  ],
  "Of": [
    "as"
  ],
  "Op": [
    "Op"
  ],
  "Others": [
    "qout"
  ],
  "PBKDF": [
    "PBKDF"
  ],
  "PRF": [
    "PRF"
  ],
  "PW": [
    "Password"
  ],
  "Paas": [
    "thow"
  ],
  "Param": [
    "prams"
  ],
  "Params": [
    "xmarck"
  ],
  "Passcode": [
    "Passcode"
  ],
  "Pending": [
    "sepe"
  ],
  "Per": [
    "percent"
  ],
  "Peson": [
    "Myinfo"
  ],
  "Pprocess": [
    "process"
  ],
  "Preamble": [
    "broadcast"
  ],
  "Prioritization": [
    "Prioritization"
  ],
  "Prioritizaton": [
    "privatization"
  ],
  "Protocol": [
    "Protocol"
  ],
  "Pwd": [
    "Password"
  ],
  "QQ": [
    "QQ"
  ],
  "Qd": [
    "channel"
  ],
  "Qiniu": [
    "Das"
  ],
  "REALTIME": [
    "REALTIME"
  ],
  "RESTAPI": [
    "E"
  ],
  "RET": [
    "RET"
  ],
  "RGBCOLOR": [
    "rgbColor"
  ],
  "RTM": [
    "RON"
  ],
  "RTMURL": [
    "retino"
  ],
  "Reachability": [
    "Reachability"
  ],
  "Redirection": [
    "direction"
  ],
  "Regex": [
    "resix"
  ],
  "Regist": [
    "Register"
  ],
  "Req": [
    "Response"
  ],
  "Rgb": [
    "Rgb"
  ],
  "Ronnection": [
    "connect"
  ],
  "Router": [
    "e"
  ],
  "S3": [
    "get"
  ],
  "SDK": [
    "SDK"
  ],
  "SDKINTERFACE": [
    "SDKINTERFACE"
  ],
  "SEL": [
    "SEL"
  ],
  "SENDDAILY": [
    "SENDDAILY"
  ],
  "SENDWIFIONLY": [
    "SENDWIFIONLY"
  ],
  "SESSIONID": [
    "SESSIONID"
  ],
  "SH": [
    "ST"
  ],
  "SHA1": [
    "SHA1"
  ],
  "SHA1hlen": [
    "SHA1hlen"
  ],
  "SHA224": [
    "SHA224"
  ],
  "SHA224hlen": [
    "SHA224hlen"
  ],
  "SHA256": [
    "SHA256"
  ],
  "SHA256hlen": [
    "SHA256hlen"
  ],
  "SHA384": [
    "SHA384"
  ],
  "SHA384hlen": [
    "SHA384hlen"
  ],
  "SHA512": [
    "SHA512"
  ],
  "SHA512hlen": [
    "SHA512hlen"
  ],
  "SQL": [
    "SRL"
  ],
  "SRLVALUEFMT": [
    "SRLVALUEFMT"
  ],
  "SSL": [
    "SSL"
  ],
  "STRUCT": [
    "STRUCT"
  ],
  "SWICH": [
    "switch"
  ],
  "Scheduler": [
    "Richeng"
  ],
  "Serializers": [
    "Serialize"
  ],
  "Simulator": [
    "mojing"
  ],
  "Spacer": [
    "Space"
  ],
  "Sscale": [
    "sScale"
  ],
  "St": [
    "1"
  ],
  "Statistic": [
    "Jintai"
  ],
  "Stats": [
    "sta"
  ],
  "Stoppped": [
    "Ting"
  ],
  "Str": [
    "Str"
  ],
  "Strat": [
    "Kai"
  ],
  "Subclass": [
    "sbuobj"
  ],
  "Subclassing": [
    "Subclassing"
  ],
  "Subqueries": [
    "getinfo"
  ],
  "Subviews": [
    "Subviews"
  ],
  "Swizzling": [
    "Swizzling"
  ],
  "Synchonization": [
    "Synchonization"
  ],
  "TF": [
    "TextFiled"
  ],
  "TIL": [
    "ITL"
  ],
  "TP": [
    "Tp"
  ],
  "TTL": [
    "SSL"
  ],
  "Tabbar": [
    "Tabbar"
  ],
  "Tapset": [
    "tapAction"
  ],
  "Tel": [
    "Tel"
  ],
  "Textfield": [
    "TextField"
  ],
  "Than": [
    "or"
  ],
  "This": [
    "A"
  ],
  "Thumbnail": [
    "littil"
  ],
  "Tiao": [
    "Tiao"
  ],
  "Timeline": [
    "Timeline"
  ],
  "Timeout": [
    "Timeout"
  ],
  "Timestamp": [
    "timeString"
  ],
  "Timestr": [
    "dateString"
  ],
  "To": [
    "to"
  ],
  "Toppic": [
    "hua"
  ],
  "Toppics": [
    "huati"
  ],
  "Tou": [
    "Tou"
  ],
  "Tracker": [
    "Tracker"
  ],
  "Trans": [
    "transaction"
  ],
  "UD": [
    "UD"
  ],
  "UI": [
    "UI"
  ],
  "UIKIT": [
    "UIKIT"
  ],
  "UIVC": [
    "UIVIewController"
  ],
  "UNAILABLE": [
    "CANRUN"
  ],
  "UR": [
    "UR"
  ],
  "URI": [
    "Uri"
  ],
  "URL": [
    "Url"
  ],
  "UTF8": [
    "UTF"
  ],
  "UTMA": [
    "UTMA"
  ],
  "UUID": [
    "UUID"
  ],
  "Unauto": [
    "Auto"
  ],
  "Unimplemented": [
    "Unimplement"
  ],
  "Unread": [
    "noread"
  ],
  "Updated": [
    "upload"
  ],
  "Userinfo": [
    "persons"
  ],
  "Username": [
    "UserName"
  ],
  "Utils": [
    "Toll"
  ],
  "V1HMAC": [
    "v1hmac"
  ],
  "V2": [
    "V2"
  ],
  "VERIDATA": [
    "VERIDATA"
  ],
  "Val": [
    "al"
  ],
  "Veiw": [
    "View"
  ],
  "Veri": [
    "Verify"
  ],
  "Via": [
    "Via"
  ],
  "Viewcolor": [
    "Viewcolor"
  ],
  "Viewdata": [
    "setupdata"
  ],
  "WORKSPACE": [
    "WORKSPACE"
  ],
  "WP": [
    "JP"
  ],
  "WPSL": [
    "WPSL"
  ],
  "WWAN": [
    "WWan"
  ],
  "When": [
    "As"
  ],
  "Windiw": [
    "Window"
  ],
  "With": [
    "and"
  ],
  "Without": [
    "whint"
  ],
  "Wk": [
    "WK"
  ],
  "Wr": [
    "Wr"
  ],
  "XML": [
    "ST"
  ],
  "YY": [
    "YY"
  ],
  "Yijian": [
    "feedback"
  ],
  "Yilog": [
    "log"
  ],
  "Yinshi": [
    "Yinshi"
  ],
  "Yirole": [
    "role"
  ],
  "Yisdk": [
    "sdk"
  ],
  "Yiuser": [
    "user"
  ],
  "Yscle": [
    "yScale"
  ],
  "Yxfile": [
    "file"
  ],
  "Zhihui": [
    "Zhihui"
  ],
  "Zi": [
    "zixuan"
  ],
  "Zixuan": [
    "DACollectST"
  ],
  "Zixuangu": [
    "MyselfStock"
  ],
  "addbtn": [
    "pplush"
  ],
  "addimg": [
    "plshimage"
  ],
  "adverbs": [
    "adv"
  ],
  "api": [
    "api"
  ],
  "apns": [
    "key"
  ],
  "astring": [
    "aString"
  ],
  "asynchronize": [
    "asycnize"
  ],
  "atouch": [
    "touch"
  ],
  "attributes": [
    "attribution",
    "abstraction",
    "attributes"
  ],
  "attrs": [
    "attribute"
  ],
  "avlog": [
    "logtte"
  ],
  "avobject": [
    "avobj"
  ],
  "backwhite": [
    "backIamge"
  ],
  "badge": [
    "sigle"
  ],
  "ballbg": [
    "allBacgroud"
  ],
  "bezel": [
    "bezel"
  ],
  "bg": [
    "Background"
  ],
  "bool": [
    "toll"
  ],
  "cannel": [
    "cancel"
  ],
  "checksum": [
    "checksum"
  ],
  "clickselect": [
    "clickselect"
  ],
  "config": [
    "Configure"
  ],
  "confire": [
    "Confirm"
  ],
  "creat": [
    "Create"
  ],
  "creater": [
    "create"
  ],
  "cryptor": [
    "cryptor"
  ],
  "curr": [
    "current"
  ],
  "dapan": [
    "globe"
  ],
  "database": [
    "source"
  ],
  "decr": [
    "descr"
  ],
  "dequeue": [
    "queue"
  ],
  "descirbe": [
    "description"
  ],
  "descr": [
    "descr"
  ],
  "destory": [
    "diss"
  ],
  "destruction": [
    "destroy"
  ],
  "di": [
    "low"
  ],
  "douyun": [
    "duoyun"
  ],
  "encry": [
    "encry"
  ],
  "enqueue": [
    "queue"
  ],
  "eventually": [
    "normallly"
  ],
  "foget": [
    "wanji"
  ],
  "followee": [
    "foomine"
  ],
  "fucus": [
    "guanzhu"
  ],
  "fupan": [
    "backyestoday"
  ],
  "fuwu": [
    "yinshi"
  ],
  "gao": [
    "higt"
  ],
  "getset": [
    "getset"
  ],
  "gid": [
    "symob"
  ],
  "goback": [
    "GoBack"
  ],
  "gt": [
    "gift"
  ],
  "headbg": [
    "touImage"
  ],
  "headview": [
    "topview"
  ],
  "hight": [
    "hight"
  ],
  "hjbg": [
    "new"
  ],
  "html": [
    "html"
  ],
  "inc": [
    "in"
  ],
  "instance": [
    "instance"
  ],
  "into": [
    "InTo"
  ],
  "iocn": [
    "mainIcon"
  ],
  "itloadtable": [
    "tabledata"
  ],
  "ivar": [
    "new"
  ],
  "jubao": [
    "repoortAction"
  ],
  "jx": [
    "st"
  ],
  "kae": [
    "kennel"
  ],
  "katouch": [
    "touch"
  ],
  "keyword": [
    "keyword"
  ],
  "khost": [
    "host"
  ],
  "kkknil": [
    "nil"
  ],
  "knotice": [
    "notice"
  ],
  "ktext": [
    "Kcontent"
  ],
  "kupdate": [
    "update"
  ],
  "kvc": [
    "Kvc"
  ],
  "layout": [
    "layout"
  ],
  "ll": [
    "ss"
  ],
  "loadstockinfodetail": [
    "loaddataSource"
  ],
  "logout": [
    "logout"
  ],
  "lt": [
    "it"
  ],
  "maket": [
    "maketmodel"
  ],
  "migration": [
    "action"
  ],
  "minurl": [
    "fenurl"
  ],
  "my": [
    "Mine"
  ],
  "niugu": [
    "ggoodStock"
  ],
  "numcount": [
    "text"
  ],
  "obj": [
    "object"
  ],
  "orig": [
    "orig"
  ],
  "parse": [
    "prama"
  ],
  "pch": [
    "pch"
  ],
  "popback": [
    "gotback"
  ],
  "pre": [
    "will"
  ],
  "primarykey": [
    "singlekey"
  ],
  "qcloud": [
    "acloud"
  ],
  "qingtian": [
    "sunshine"
  ],
  "receip": [
    "receipt"
  ],
  "recursive": [
    "recover"
  ],
  "regisertode": [
    "registCode"
  ],
  "rekey": [
    "onekey"
  ],
  "relationfor": [
    "relations"
  ],
  "resize": [
    "resize"
  ],
  "return": [
    "return"
  ],
  "rgba": [
    "rgba"
  ],
  "rgbtn": [
    "youButton"
  ],
  "rpc": [
    "run"
  ],
  "safely": [
    "safe"
  ],
  "scrollselect": [
    "alltext"
  ],
  "selectimage": [
    "seleimg"
  ],
  "seprator": [
    "sepand"
  ],
  "serializer": [
    "serializer"
  ],
  "shangzheng": [
    "homemain"
  ],
  "shou": [
    "goodTh"
  ],
  "should": [
    "will"
  ],
  "shouye": [
    "Homepage"
  ],
  "sq": [
    "sq"
  ],
  "sqlite": [
    "sqlNew"
  ],
  "storeable": [
    "dian"
  ],
  "submint": [
    "submint"
  ],
  "suffix": [
    "suffix",
    "sixfus",
    "stfix",
    "stringSuffix",
    "wordSuffix"
  ],
  "sureclick": [
    "yesClick"
  ],
  "swizzle": [
    "swizzle"
  ],
  "synchronizable": [
    "synchron"
  ],
  "testcase": [
    "nocase"
  ],
  "tijiao": [
    "upload"
  ],
  "tilelab": [
    "tipLabel"
  ],
  "tuijian": [
    "reecom"
  ],
  "type": [
    "subType"
  ],
  "unfollow": [
    "noflow"
  ],
  "unregister": [
    "unRegister"
  ],
  "unschedule": [
    "scheduled"
  ],
  "unset": [
    "noset"
  ],
  "unsubscribe": [
    "updatescribe"
  ],
  "update": [
    "modify"
  ],
  "updown": [
    "downup"
  ],
  "uphomeviews": [
    "midHview"
  ],
  "vc": [
    "ViewController"
  ],
  "when": [
    "thenafter"
  ],
  "where": [
    "location"
  ],
  "xugujihui": [
    "zhihuiStock"
  ],
  "yan": [
    "vercode"
  ],
  "yesto": [
    "whether"
  ],
  "zd": [
    "zangdie"
  ],
  "zf": [
    "uppercent"
  ],
  "zhishu": [
    "index"
  ],
  "zhuti": [
    "topic"
  ],
  "zlab": [
    "highPlace"
  ],
  "zt": [
    "higst"
  ],
  "\u63a5\u5165": [
    "\u63a5\u5165"
  ]
}